scidantic/__init__.py
scidantic/array/__init__.py
scidantic/array/_base.py
scidantic/array/_numpy.py
scidantic-0.0.1.dist-info/METADATA
scidantic-0.0.1.dist-info/WHEEL
scidantic-0.0.1.dist-info/licenses/LICENSE
scidantic-0.0.1.dist-info/RECORD
